{
  "required": true,
  "compatibilityLevel": "JAVA_8",
  "package": "me.third.right.mixin.client",
  "refmap": "mixins.third.refmap.json",
  "minVersion": "0.4-SNAPSHOT",
  "mixins": [
    "MixinItem",
    "MixinItemBlock",
    "MixinItemRenderer",
    "MixinItemStack",
    "MixinLayerArmorBase",
    "MixinMinecraft",
    "MixinMovementInputFromOptions",
    "MixinNetworkManager",
    "MixinNetworkManagerChInit",
    "MixinPlayerControllerMP",
    "MixinWorld",
    "MixinWorldClient",
    "accessor.IBlock",
    "accessor.IBlockPos",
    "accessor.ICPacketChatMessage",
    "accessor.ICPacketCloseWindow",
    "accessor.ICPacketCustomPayload",
    "accessor.ICPacketPlayer",
    "accessor.ICPacketUseEntity",
    "accessor.IEntity",
    "accessor.IEntityPlayer",
    "accessor.IEntityRenderer",
    "accessor.IGui",
    "accessor.IGuiNewChat",
    "accessor.IGuiPlayerTabOverlay",
    "accessor.IItemFood",
    "accessor.IKeyBinding",
    "accessor.IMinecraft",
    "accessor.IPlayerControllerMP",
    "accessor.IRenderGlobal",
    "accessor.IRenderManager",
    "accessor.ISPacketChat",
    "accessor.ISPacketEffect",
    "accessor.ISPacketEntityVelocity",
    "accessor.ISPacketExplosion",
    "accessor.ISPacketPlayerPosLook",
    "accessor.ISPacketSoundEffect",
    "accessor.ITimer",
    "accessor.IVec3i",
    "baritone.MixinBaritoneSettings",
    "block.MixinBlock",
    "block.MixinBlockLiquid",
    "block.MixinBlockModelRenderer",
    "block.MixinBlockSoulSand",
    "block.MixinBlockWeb",
    "block.MixinTileEntities.MixinChestRender",
    "block.MixinTileEntities.MixinETableRender",
    "block.MixinTileEntities.MixinSignRender",
    "block.MixinTileEntities.MixinSkullRender",
    "entity.MixinAbstractHorse",
    "entity.MixinEntity",
    "entity.MixinEntityLivingBase",
    "entity.MixinEntityLlama",
    "entity.MixinEntityPig",
    "entity.MixinEntityPlayer",
    "entity.MixinEntityPlayerSP",
    "entity.MixinEntityRenderer",
    "gui.MixinGuiBossOverlay",
    "gui.MixinGuiConnecting",
    "gui.MixinGuiDisconnected",
    "gui.MixinGuiInGame",
    "gui.MixinGuiMainMenu",
    "gui.MixinGuiNewChat",
    "gui.MixinGuiPlayerTabOverlay",
    "gui.MixinGuiScreen",
    "render.MixinBufferBuilder",
    "render.MixinRender",
    "render.MixinRenderEnderCrystal",
    "render.MixinRenderGlobal",
    "render.MixinRenderItem",
    "render.MixinRenderLivingBase",
    "render.MixinRenderPlayer",
    "render.MixinVisGraph"
  ]
}
